speaker_verification_toolkit/__init__.py
speaker_verification_toolkit/tools.py
speaker_verification_toolkit-0.0.2.dist-info/LICENSE
speaker_verification_toolkit-0.0.2.dist-info/METADATA
speaker_verification_toolkit-0.0.2.dist-info/WHEEL
speaker_verification_toolkit-0.0.2.dist-info/top_level.txt
speaker_verification_toolkit-0.0.2.dist-info/RECORD
