Metadata-Version: 2.1
Name: speaker_verification_toolkit
Version: 0.0.2
Summary: A package designed to compose speaker verification systems
Home-page: https://github.com/Alohomora-team/speaker-verification-toolkit
Author: Alohomora Team
Author-email: alohomorafga@gmail.com
License: UNKNOWN
Platform: UNKNOWN
Classifier: Programming Language :: Python :: 3
Classifier: License :: OSI Approved :: MIT License
Classifier: Operating System :: OS Independent
Requires-Python: >=3.6
